<md:EntityDescriptor xmlns:init="urn:oasis:names:tc:SAML:profiles:SSO:request-init" xmlns:md="urn:oasis:names:tc:SAML:2.0:metadata" xmlns:mdrpi="urn:oasis:names:tc:SAML:metadata:rpi" xmlns:ds="http://www.w3.org/2000/09/xmldsig#" entityID="https://shibboleth-sp.prod.proquest.com/shibboleth">
    <md:Extensions>
      <DigestMethod xmlns="urn:oasis:names:tc:SAML:metadata:algsupport" Algorithm="http://www.w3.org/2001/04/xmlenc#sha512"/>
      <DigestMethod xmlns="urn:oasis:names:tc:SAML:metadata:algsupport" Algorithm="http://www.w3.org/2001/04/xmldsig-more#sha384"/>
      <DigestMethod xmlns="urn:oasis:names:tc:SAML:metadata:algsupport" Algorithm="http://www.w3.org/2001/04/xmlenc#sha256"/>
      <DigestMethod xmlns="urn:oasis:names:tc:SAML:metadata:algsupport" Algorithm="http://www.w3.org/2001/04/xmldsig-more#sha224"/>
      <DigestMethod xmlns="urn:oasis:names:tc:SAML:metadata:algsupport" Algorithm="http://www.w3.org/2000/09/xmldsig#sha1"/>
      <SigningMethod xmlns="urn:oasis:names:tc:SAML:metadata:algsupport" Algorithm="http://www.w3.org/2001/04/xmldsig-more#ecdsa-sha512"/>
      <SigningMethod xmlns="urn:oasis:names:tc:SAML:metadata:algsupport" Algorithm="http://www.w3.org/2001/04/xmldsig-more#ecdsa-sha384"/>
      <SigningMethod xmlns="urn:oasis:names:tc:SAML:metadata:algsupport" Algorithm="http://www.w3.org/2001/04/xmldsig-more#ecdsa-sha256"/>
      <SigningMethod xmlns="urn:oasis:names:tc:SAML:metadata:algsupport" Algorithm="http://www.w3.org/2001/04/xmldsig-more#ecdsa-sha224"/>
      <SigningMethod xmlns="urn:oasis:names:tc:SAML:metadata:algsupport" Algorithm="http://www.w3.org/2001/04/xmldsig-more#rsa-sha512"/>
      <SigningMethod xmlns="urn:oasis:names:tc:SAML:metadata:algsupport" Algorithm="http://www.w3.org/2001/04/xmldsig-more#rsa-sha384"/>
      <SigningMethod xmlns="urn:oasis:names:tc:SAML:metadata:algsupport" Algorithm="http://www.w3.org/2001/04/xmldsig-more#rsa-sha256"/>
      <SigningMethod xmlns="urn:oasis:names:tc:SAML:metadata:algsupport" Algorithm="http://www.w3.org/2009/xmldsig11#dsa-sha256"/>
      <SigningMethod xmlns="urn:oasis:names:tc:SAML:metadata:algsupport" Algorithm="http://www.w3.org/2001/04/xmldsig-more#ecdsa-sha1"/>
      <SigningMethod xmlns="urn:oasis:names:tc:SAML:metadata:algsupport" Algorithm="http://www.w3.org/2000/09/xmldsig#rsa-sha1"/>
      <SigningMethod xmlns="urn:oasis:names:tc:SAML:metadata:algsupport" Algorithm="http://www.w3.org/2000/09/xmldsig#dsa-sha1"/>
      <mdrpi:RegistrationInfo registrationAuthority="http://ukfederation.org.uk" registrationInstant="2014-08-14T16:15:53Z">
        <mdrpi:RegistrationPolicy xml:lang="en">http://ukfederation.org.uk/doc/mdrps-20130902</mdrpi:RegistrationPolicy>
      </mdrpi:RegistrationInfo>
    </md:Extensions>
    <md:SPSSODescriptor protocolSupportEnumeration="urn:oasis:names:tc:SAML:2.0:protocol urn:oasis:names:tc:SAML:1.1:protocol urn:oasis:names:tc:SAML:1.0:protocol">
      <md:Extensions>
        <init:RequestInitiator Binding="urn:oasis:names:tc:SAML:profiles:SSO:request-init" Location="https://shibboleth-sp.prod.proquest.com/Shibboleth.sso/DS"/>
      </md:Extensions>
      <md:KeyDescriptor>
        <ds:KeyInfo>
          <ds:X509Data>
            <ds:X509Certificate>
						MIIDWTCCAkGgAwIBAgIJALUXgtUwAcW1MA0GCSqGSIb3DQEBBQUAMCoxKDAmBgNV
						BAMTH3NoaWJib2xldGgtc3AucHJvZC5wcm9xdWVzdC5jb20wHhcNMTQwODA0MTgx
						NjMxWhcNMTcwODA0MTgxNjMxWjAqMSgwJgYDVQQDEx9zaGliYm9sZXRoLXNwLnBy
						b2QucHJvcXVlc3QuY29tMIIBIjANBgkqhkiG9w0BAQEFAAOCAQ8AMIIBCgKCAQEA
						uL3AvdPUloVAT2SxU5zfIMS1Q51dz15rM97hcspWkeJbOJRzuWGmdn1NTO8wNgfH
						WMcvxCH+MlUZdixFEEZ/oghDCKYQyngBe5DFb1o2MmXyXidtaFVzKOdkvwkrGNB4
						AEAg0ee6EN72qxlUSk3md90GWsv2RVOicpxwKcpk/f8ibfuaqwUZoqyzBM9/jADp
						uBG3iyiNr1/uGvCBhghvTpHRjZ6+L1t1tY8fi9xs15kd8k5nxQi1BSoGcqkmGJXB
						OwBhn5mb5FjHGbzw6kbL/O+zWBLlzIIJmS3YsbgBiAGWbzIdGl366VRkea0yuVQE
						KybgYDA/W5ezLNSeEdmMlwIDAQABo4GBMH8wXgYDVR0RBFcwVYIfc2hpYmJvbGV0
						aC1zcC5wcm9kLnByb3F1ZXN0LmNvbYYyaHR0cHM6Ly9zaGliYm9sZXRoLXNwLnBy
						b2QucHJvcXVlc3QuY29tL3NoaWJib2xldGgwHQYDVR0OBBYEFGaLI8FVRsbPeB4H
						Q2517x6lRlkqMA0GCSqGSIb3DQEBBQUAA4IBAQCqcb5MKykmiQCSv19us1E1+gk5
						LWew6OUY/rWRdM9EpVbKlMgo0A2KTuJ5qrI/miS69wv+5nbEPax007kP7Xd4e54K
						yK0KWmTt92O3Rie2uf1dIF/VDOaIGvny0WTNfgiRmGrq3KERz26j7vQXbk9WOdp3
						+L3v1Wr8+1N/MLrQ7JDZAygO3Xb4gGcGI9VWlPKL8o09K4fR8EM97p3qeqJINMqw
						QsWrBhm9Tb51QxpARIjlF8paFZ0h6ugS/thDOh50wvqJ8B0r3ozD6E2Mu3A0zF/o
						J4Wfgn170Gts8ghZeFrntOIilzGjb13VgnUpVXqsMEkmYqtzmKOGxiVuIyXc
					</ds:X509Certificate>
          </ds:X509Data>
        </ds:KeyInfo>
        <md:EncryptionMethod Algorithm="http://www.w3.org/2009/xmlenc11#aes128-gcm"/>
        <md:EncryptionMethod Algorithm="http://www.w3.org/2009/xmlenc11#aes192-gcm"/>
        <md:EncryptionMethod Algorithm="http://www.w3.org/2009/xmlenc11#aes256-gcm"/>
        <md:EncryptionMethod Algorithm="http://www.w3.org/2001/04/xmlenc#aes128-cbc"/>
        <md:EncryptionMethod Algorithm="http://www.w3.org/2001/04/xmlenc#aes192-cbc"/>
        <md:EncryptionMethod Algorithm="http://www.w3.org/2001/04/xmlenc#aes256-cbc"/>
        <md:EncryptionMethod Algorithm="http://www.w3.org/2001/04/xmlenc#tripledes-cbc"/>
        <md:EncryptionMethod Algorithm="http://www.w3.org/2009/xmlenc11#rsa-oaep"/>
        <md:EncryptionMethod Algorithm="http://www.w3.org/2001/04/xmlenc#rsa-oaep-mgf1p"/>
      </md:KeyDescriptor>
      <md:ArtifactResolutionService Binding="urn:oasis:names:tc:SAML:2.0:bindings:SOAP" Location="https://shibboleth-sp.prod.proquest.com/Shibboleth.sso/Artifact/SOAP" index="1"/>
      <md:SingleLogoutService Binding="urn:oasis:names:tc:SAML:2.0:bindings:SOAP" Location="https://shibboleth-sp.prod.proquest.com/Shibboleth.sso/SLO/SOAP"/>
      <md:SingleLogoutService Binding="urn:oasis:names:tc:SAML:2.0:bindings:HTTP-Redirect" Location="https://shibboleth-sp.prod.proquest.com/Shibboleth.sso/SLO/Redirect"/>
      <md:SingleLogoutService Binding="urn:oasis:names:tc:SAML:2.0:bindings:HTTP-POST" Location="https://shibboleth-sp.prod.proquest.com/Shibboleth.sso/SLO/POST"/>
      <md:SingleLogoutService Binding="urn:oasis:names:tc:SAML:2.0:bindings:HTTP-Artifact" Location="https://shibboleth-sp.prod.proquest.com/Shibboleth.sso/SLO/Artifact"/>
      <md:ManageNameIDService Binding="urn:oasis:names:tc:SAML:2.0:bindings:SOAP" Location="https://shibboleth-sp.prod.proquest.com/Shibboleth.sso/NIM/SOAP"/>
      <md:ManageNameIDService Binding="urn:oasis:names:tc:SAML:2.0:bindings:HTTP-Redirect" Location="https://shibboleth-sp.prod.proquest.com/Shibboleth.sso/NIM/Redirect"/>
      <md:ManageNameIDService Binding="urn:oasis:names:tc:SAML:2.0:bindings:HTTP-POST" Location="https://shibboleth-sp.prod.proquest.com/Shibboleth.sso/NIM/POST"/>
      <md:ManageNameIDService Binding="urn:oasis:names:tc:SAML:2.0:bindings:HTTP-Artifact" Location="https://shibboleth-sp.prod.proquest.com/Shibboleth.sso/NIM/Artifact"/>
      <md:AssertionConsumerService Binding="urn:oasis:names:tc:SAML:2.0:bindings:HTTP-POST" Location="https://shibboleth-sp.prod.proquest.com/Shibboleth.sso/SAML2/POST" index="1"/>
      <md:AssertionConsumerService Binding="urn:oasis:names:tc:SAML:2.0:bindings:HTTP-POST-SimpleSign" Location="https://shibboleth-sp.prod.proquest.com/Shibboleth.sso/SAML2/POST-SimpleSign" index="2"/>
      <md:AssertionConsumerService Binding="urn:oasis:names:tc:SAML:2.0:bindings:HTTP-Artifact" Location="https://shibboleth-sp.prod.proquest.com/Shibboleth.sso/SAML2/Artifact" index="3"/>
      <md:AssertionConsumerService Binding="urn:oasis:names:tc:SAML:2.0:bindings:PAOS" Location="https://shibboleth-sp.prod.proquest.com/Shibboleth.sso/SAML2/ECP" index="4"/>
      <md:AssertionConsumerService Binding="urn:oasis:names:tc:SAML:1.0:profiles:browser-post" Location="https://shibboleth-sp.prod.proquest.com/Shibboleth.sso/SAML/POST" index="5"/>
      <md:AssertionConsumerService Binding="urn:oasis:names:tc:SAML:1.0:profiles:artifact-01" Location="https://shibboleth-sp.prod.proquest.com/Shibboleth.sso/SAML/Artifact" index="6"/>
    </md:SPSSODescriptor>
    <md:Organization>
      <md:OrganizationName xml:lang="en">Proquest Information and Learning Limited</md:OrganizationName>
      <md:OrganizationDisplayName xml:lang="en">ProQuest</md:OrganizationDisplayName>
      <md:OrganizationURL xml:lang="en">http://www.proquest.com/</md:OrganizationURL>
    </md:Organization>
    <md:ContactPerson contactType="support">
      <md:GivenName>Technical Support Team</md:GivenName>
      <md:EmailAddress>mailto:support@proquest.com</md:EmailAddress>
    </md:ContactPerson>
    <md:ContactPerson contactType="technical">
      <md:GivenName>Paul</md:GivenName>
      <md:SurName>Wilt</md:SurName>
      <md:EmailAddress>mailto:pqshibbolethtech@proquest.com</md:EmailAddress>
    </md:ContactPerson>
  </md:EntityDescriptor>